easyshell/__init__.py
easyshell/__main__.py
easyshell-0.16.dist-info/DESCRIPTION.rst
easyshell-0.16.dist-info/METADATA
easyshell-0.16.dist-info/RECORD
easyshell-0.16.dist-info/WHEEL
easyshell-0.16.dist-info/metadata.json
easyshell-0.16.dist-info/top_level.txt
