Metadata-Version: 2.0
Name: easyshell
Version: 0.16
Summary: Library for creating recursive shells.
Home-page: https://github.com/qzmfranklin/easyshell
Author: Zhongming Qu
Author-email: qzmfranklin@gmail.com
License: ['GPL3']
Keywords: shell
Platform: UNKNOWN
Classifier: Programming Language :: Python :: 3
Classifier: Intended Audience :: Developers
Classifier: Operating System :: OS Independent
